{
  "ogmoVersion": "3.4.0",
  "width": 1360,
  "height": 720,
  "offsetX": 0,
  "offsetY": 0,
  "values": {"hasBackground": false},
  "layers": [
    {
      "name": "Assets",
      "_eid": "42126934",
      "offsetX": 0,
      "offsetY": 0,
      "gridCellWidth": 40,
      "gridCellHeight": 40,
      "gridCellsX": 34,
      "gridCellsY": 18,
      "entities": [
        {
          "name": "Sprite",
          "id": 0,
          "_eid": "42067692",
          "x": 760,
          "y": 80,
          "width": 40,
          "height": 40,
          "originX": 0,
          "originY": 0,
          "values": {"rescale": true, "hasYSort": true, "spritePath": "proj:../../Sprites/Overworld/Assets/sign.png"}
        },
        {
          "name": "Sprite",
          "id": 1,
          "_eid": "42067692",
          "x": 600,
          "y": 240,
          "width": 40,
          "height": 40,
          "originX": 0,
          "originY": 0,
          "values": {"rescale": false, "hasYSort": true, "spritePath": "proj:../../Sprites/Overworld/Assets/tree.png"}
        },
        {
          "name": "Sprite",
          "id": 2,
          "_eid": "42067692",
          "x": 400,
          "y": 560,
          "width": 40,
          "height": 40,
          "originX": 0,
          "originY": 0,
          "values": {"rescale": false, "hasYSort": true, "spritePath": "proj:../../Sprites/Overworld/Assets/tree.png"}
        }
      ]
    },
    {
      "name": "Triggers",
      "_eid": "42027604",
      "offsetX": 0,
      "offsetY": 0,
      "gridCellWidth": 40,
      "gridCellHeight": 40,
      "gridCellsX": 34,
      "gridCellsY": 18,
      "entities": [
        {
          "name": "Interactable",
          "id": 0,
          "_eid": "42030714",
          "x": 400,
          "y": 440,
          "width": 80,
          "height": 80,
          "originX": 0,
          "originY": 0,
          "values": {"dialogueID": "start", "dialoguesTotal": 1}
        },
        {
          "name": "Interactable",
          "id": 1,
          "_eid": "42030714",
          "x": 760,
          "y": 80,
          "width": 40,
          "height": 40,
          "originX": 0,
          "originY": 0,
          "values": {"dialogueID": "multi", "dialoguesTotal": 2}
        },
        {
          "name": "Battle",
          "id": 2,
          "_eid": "62280486",
          "x": 880,
          "y": 120,
          "width": 80,
          "height": 80,
          "originX": 0,
          "originY": 0,
          "values": {"encounterName": "Example"}
        },
        {
          "name": "Door",
          "id": 4,
          "_eid": "30097684",
          "x": 1320,
          "y": 360,
          "width": 40,
          "height": 80,
          "originX": 0,
          "originY": 0,
          "values": {"roomNext": "Room2", "originID": 1, "nextBGM": ""}
        }
      ]
    },
    {
      "name": "AvatarOrigin",
      "_eid": "42017888",
      "offsetX": 0,
      "offsetY": 0,
      "gridCellWidth": 8,
      "gridCellHeight": 8,
      "gridCellsX": 170,
      "gridCellsY": 90,
      "entities": [
        {
          "name": "Player",
          "id": 0,
          "_eid": "41975265",
          "x": 112,
          "y": 384,
          "originX": 0,
          "originY": 76,
          "values": {"direction": 2, "originID": 1}
        },
        {
          "name": "Player",
          "id": 1,
          "_eid": "41975265",
          "x": 16,
          "y": 384,
          "originX": 0,
          "originY": 76,
          "values": {"direction": 1, "originID": 3}
        },
        {
          "name": "Player",
          "id": 2,
          "_eid": "41975265",
          "x": 1264,
          "y": 416,
          "originX": 0,
          "originY": 76,
          "values": {"direction": 3, "originID": 2}
        }
      ]
    },
    {
      "name": "solid",
      "_eid": "68263052",
      "offsetX": 0,
      "offsetY": 0,
      "gridCellWidth": 40,
      "gridCellHeight": 40,
      "gridCellsX": 34,
      "gridCellsY": 18,
      "tileset": "blank40",
      "data2D": [
        [-1, -1, -1, -1, -1, -1, -1, -1, -1, -1, -1, -1, -1, -1, -1, -1, -1, 0, 0, 0, 0, 0, -1, -1, -1, -1, -1, -1, -1, -1, -1, -1, -1, -1],
        [-1, -1, -1, -1, -1, -1, -1, -1, -1, -1, -1, -1, -1, -1, -1, -1, -1, 0, -1, -1, -1, 0, -1, -1, -1, -1, -1, -1, -1, -1, -1, -1, -1, -1],
        [-1, -1, -1, 0, 0, 0, 0, 0, 0, 0, 0, 0, 0, 0, 0, 0, 0, 0, -1, 0, -1, 0, 0, 0, 0, -1, -1, -1, -1, -1, -1, -1, -1, -1],
        [-1, -1, -1, 0, -1, -1, -1, -1, -1, -1, -1, -1, -1, -1, -1, -1, -1, -1, -1, -1, -1, -1, -1, -1, 0, -1, -1, -1, -1, -1, -1, -1, -1, -1],
        [-1, -1, -1, 0, -1, -1, -1, -1, -1, -1, -1, -1, -1, -1, -1, -1, -1, -1, -1, -1, -1, -1, -1, -1, 0, -1, -1, -1, -1, -1, -1, -1, -1, -1],
        [-1, -1, -1, 0, -1, -1, 0, 0, 0, 0, 0, 0, 0, 0, 0, 0, 0, 0, 0, 0, 0, 0, -1, -1, 0, -1, -1, -1, -1, -1, -1, -1, -1, -1],
        [-1, -1, -1, 0, -1, -1, 0, -1, -1, -1, -1, -1, -1, -1, -1, -1, -1, -1, -1, -1, -1, 0, -1, -1, 0, -1, -1, -1, -1, -1, -1, -1, -1, -1],
        [0, 0, 0, 0, -1, -1, 0, -1, -1, -1, -1, -1, -1, -1, -1, -1, -1, -1, -1, -1, -1, 0, -1, -1, 0, -1, -1, -1, -1, -1, -1, -1, -1, -1],
        [-1, -1, -1, -1, -1, -1, 0, -1, -1, -1, -1, -1, -1, -1, -1, -1, -1, -1, -1, -1, -1, 0, -1, -1, 0, 0, 0, 0, 0, 0, 0, 0, 0, 0],
        [-1, -1, -1, -1, -1, -1, 0, -1, 0, 0, 0, 0, 0, -1, -1, -1, -1, -1, -1, -1, -1, 0, -1, -1, -1, -1, -1, -1, -1, -1, -1, -1, -1, -1],
        [0, 0, 0, 0, -1, -1, 0, -1, 0, -1, -1, -1, 0, -1, -1, -1, -1, -1, -1, -1, -1, 0, -1, -1, -1, -1, -1, -1, -1, -1, -1, -1, -1, -1],
        [-1, -1, -1, 0, -1, -1, 0, -1, 0, -1, -1, -1, 0, -1, -1, -1, -1, -1, -1, -1, -1, 0, -1, -1, 0, 0, 0, 0, 0, 0, 0, 0, 0, 0],
        [-1, -1, -1, 0, -1, -1, 0, -1, 0, -1, -1, -1, 0, -1, -1, -1, -1, -1, -1, -1, -1, 0, -1, -1, 0, -1, -1, -1, -1, -1, -1, -1, -1, -1],
        [-1, -1, -1, 0, -1, -1, 0, -1, 0, -1, -1, -1, 0, -1, -1, -1, -1, -1, -1, -1, -1, 0, -1, -1, 0, -1, -1, -1, -1, -1, -1, -1, -1, -1],
        [-1, -1, -1, 0, -1, -1, 0, 0, 0, -1, -1, -1, 0, 0, 0, 0, 0, 0, 0, 0, 0, 0, -1, -1, 0, -1, -1, -1, -1, -1, -1, -1, -1, -1],
        [-1, -1, -1, 0, -1, -1, -1, -1, -1, -1, -1, -1, -1, -1, -1, -1, -1, -1, -1, -1, -1, -1, -1, -1, 0, -1, -1, -1, -1, -1, -1, -1, -1, -1],
        [-1, -1, -1, 0, -1, -1, -1, -1, -1, -1, -1, -1, -1, -1, -1, -1, -1, -1, -1, -1, -1, -1, -1, -1, 0, -1, -1, -1, -1, -1, -1, -1, -1, -1],
        [-1, -1, -1, 0, 0, 0, 0, 0, 0, 0, 0, 0, 0, 0, 0, 0, 0, 0, 0, 0, 0, 0, 0, 0, 0, -1, -1, -1, -1, -1, -1, -1, -1, -1]
      ],
      "exportMode": 0,
      "arrayMode": 1
    },
    {
      "name": "Ground",
      "_eid": "41973050",
      "offsetX": 0,
      "offsetY": 0,
      "gridCellWidth": 40,
      "gridCellHeight": 40,
      "gridCellsX": 34,
      "gridCellsY": 18,
      "tileset": "field",
      "data2D": [
        [-1, -1, -1, -1, -1, -1, -1, -1, -1, -1, -1, -1, -1, -1, -1, -1, -1, -1, -1, -1, -1, -1, -1, -1, -1, -1, -1, -1, -1, -1, -1, -1, -1, -1],
        [-1, -1, -1, -1, -1, -1, -1, -1, -1, -1, -1, -1, -1, -1, -1, -1, -1, -1, 0, 0, 0, -1, -1, -1, -1, -1, -1, -1, -1, -1, -1, -1, -1, -1],
        [-1, -1, -1, -1, -1, -1, -1, -1, -1, -1, -1, -1, -1, -1, -1, -1, -1, -1, 0, 0, 0, -1, -1, -1, -1, -1, -1, -1, -1, -1, -1, -1, -1, -1],
        [-1, -1, -1, -1, 0, 0, 0, 0, 0, 0, 0, 0, 0, 0, 0, 0, 0, 0, 0, 0, 0, 0, 0, 0, -1, -1, -1, -1, -1, -1, -1, -1, -1, -1],
        [-1, -1, -1, -1, 0, 0, 0, 0, 0, 0, 0, 0, 0, 0, 0, 0, 0, 0, 0, 0, 0, 0, 0, 0, -1, -1, -1, -1, -1, -1, -1, -1, -1, -1],
        [-1, -1, -1, -1, 0, 0, -1, -1, -1, -1, -1, -1, -1, -1, -1, -1, -1, -1, -1, -1, -1, -1, 0, 0, -1, -1, -1, -1, -1, -1, -1, -1, -1, -1],
        [-1, -1, -1, -1, 0, 0, -1, -1, -1, -1, -1, -1, -1, -1, -1, -1, -1, -1, -1, -1, -1, -1, 0, 0, -1, -1, -1, -1, -1, -1, -1, -1, -1, -1],
        [-1, -1, -1, -1, 0, 0, -1, -1, -1, -1, -1, -1, -1, -1, -1, -1, -1, -1, -1, -1, -1, -1, 0, 0, -1, -1, -1, -1, -1, -1, -1, -1, -1, -1],
        [0, 0, 0, 0, 0, 0, -1, -1, -1, -1, -1, -1, -1, -1, -1, -1, -1, -1, -1, -1, -1, -1, 0, 0, -1, -1, -1, -1, -1, -1, -1, -1, -1, -1],
        [0, 0, 0, 0, 0, 0, -1, -1, -1, -1, -1, -1, -1, -1, -1, -1, -1, -1, -1, -1, -1, -1, 0, 0, 0, 0, 0, 0, 0, 0, 0, 0, 0, 0],
        [-1, -1, -1, -1, 0, 0, -1, -1, -1, 0, 0, 0, -1, -1, -1, -1, -1, -1, -1, -1, -1, -1, 0, 0, 0, 0, 0, 0, 0, 0, 0, 0, 0, 0],
        [-1, -1, -1, -1, 0, 0, -1, -1, -1, 0, 0, 0, -1, -1, -1, -1, -1, -1, -1, -1, -1, -1, 0, 0, -1, -1, -1, -1, -1, -1, -1, -1, -1, -1],
        [-1, -1, -1, -1, 0, 0, -1, -1, -1, 0, 0, 0, -1, -1, -1, -1, -1, -1, -1, -1, -1, -1, 0, 0, -1, -1, -1, -1, -1, -1, -1, -1, -1, -1],
        [-1, -1, -1, -1, 0, 0, -1, -1, -1, -1, -1, -1, -1, -1, -1, -1, -1, -1, -1, -1, -1, -1, 0, 0, -1, -1, -1, -1, -1, -1, -1, -1, -1, -1],
        [-1, -1, -1, -1, 0, 0, -1, -1, -1, -1, -1, -1, -1, -1, -1, -1, -1, -1, -1, -1, -1, -1, 0, 0, -1, -1, -1, -1, -1, -1, -1, -1, -1, -1],
        [-1, -1, -1, -1, 0, 0, 0, 0, 0, 0, 0, 0, 0, 0, 0, 0, 0, 0, 0, 0, 0, 0, 0, 0, -1, -1, -1, -1, -1, -1, -1, -1, -1, -1],
        [-1, -1, -1, -1, 0, 0, 0, 0, 0, 0, 0, 0, 0, 0, 0, 0, 0, 0, 0, 0, 0, 0, 0, 0, -1, -1, -1, -1, -1, -1, -1, -1, -1, -1],
        [-1, -1, -1, -1, -1, -1, -1, -1, -1, -1, -1, -1, -1, -1, -1, -1, -1, -1, -1, -1, -1, -1, -1, -1, -1, -1, -1, -1, -1, -1, -1, -1, -1, -1]
      ],
      "exportMode": 0,
      "arrayMode": 1
    }
  ]
}